{
 "date": "2022-01-20",
 "buildid": "20220120100401",
 "cset": "3ddab45ce6bdbc0501b54ae64cbef202e8f92fb5",
 "bugs": [
  {
   "bugid": 1745511,
   "status": "RESOLVED",
   "component": "Core:Audio/Video: GMP",
   "summary": "Expand FOG IPC to GMP process"
  },
  {
   "bugid": 1750810,
   "status": "ASSIGNED",
   "component": "Core:Audio/Video: cubeb",
   "summary": "Disable AudioIPC rework on Linux until known issues are resolved"
  },
  {
   "bugid": 1747934,
   "status": "RESOLVED",
   "component": "Core:CSS Parsing and Computation",
   "summary": "::marker does not support CSS property line-height"
  },
  {
   "bugid": 1750483,
   "status": "RESOLVED",
   "component": "Core:CSS Parsing and Computation",
   "summary": "\"ThreeDFace\" should have enough contrast for \"ButtonText\" on the dark color scheme mode"
  },
  {
   "bugid": 1750980,
   "status": "RESOLVED",
   "component": "Core:Canvas: WebGL",
   "summary": "Crash in [@ mozilla::SVGObserverUtils::InvalidateDirectRenderingObservers]"
  },
  {
   "bugid": 1709790,
   "status": "RESOLVED",
   "component": "Core:DOM: Core & HTML",
   "summary": "Add support for element.outerText"
  },
  {
   "bugid": 1750868,
   "status": "RESOLVED",
   "component": "Core:DOM: Core & HTML",
   "summary": "Limit dom.maxHardwareConcurrency to 16 on beta and release"
  },
  {
   "bugid": 1750931,
   "status": "RESOLVED",
   "component": "Core:DOM: Core & HTML",
   "summary": "Fix non-unified-build bustage in dom/events, dom/fetch and dom/streams"
  },
  {
   "bugid": 1748647,
   "status": "RESOLVED",
   "component": "Core:DOM: Device Interfaces",
   "summary": "MIDI messages are delivered twice if the same port is opened twice"
  },
  {
   "bugid": 1748902,
   "status": "RESOLVED",
   "component": "Core:DOM: Streams",
   "summary": "Correct handling of uncatchable exceptions inside of underlying source callbacks."
  },
  {
   "bugid": 1750564,
   "status": "RESOLVED",
   "component": "Core:DOM: Streams",
   "summary": "Implement readable byte streams"
  },
  {
   "bugid": 1748450,
   "status": "RESOLVED",
   "component": "Core:Disability Access APIs",
   "summary": "Grabbing focus and/or setting caret should either not cause object destruction or should do it more quickly"
  },
  {
   "bugid": 1748775,
   "status": "RESOLVED",
   "component": "Core:Disability Access APIs",
   "summary": "Crash in [@ objc_msgSend | -[mozColumnContainer moxUnignoredChildren]]"
  },
  {
   "bugid": 1749762,
   "status": "RESOLVED",
   "component": "Core:Disability Access APIs",
   "summary": "my .xsession-errors log is still flooded with the same error signal name 'load_complete' is invalid for instance '0x7fcb46e0d230' of type 'MaiAtkType139'"
  },
  {
   "bugid": 1750550,
   "status": "RESOLVED",
   "component": "Core:Disability Access APIs",
   "summary": "Crash in [@ PLDHashTable::Iterator::Iterator | ConvertToAtkTextAttributeSet]"
  },
  {
   "bugid": 1750680,
   "status": "RESOLVED",
   "component": "Core:Disability Access APIs",
   "summary": "AccessibleChildren fails in-process on an OOP iframe with overridden role"
  },
  {
   "bugid": 1688999,
   "status": "RESOLVED",
   "component": "Core:Graphics",
   "summary": "Crash in [@ mozalloc_abort | std::string::string | mozilla::gl::GLContext::InitImpl]"
  },
  {
   "bugid": 1750866,
   "status": "ASSIGNED",
   "component": "Core:Graphics: WebGPU",
   "summary": "\"Wrong data size\" error in WebGPU writeTexture"
  },
  {
   "bugid": 1695318,
   "status": "RESOLVED",
   "component": "Core:Graphics: WebRender",
   "summary": "Black patches appear in a 3d tour on youriguide.com"
  },
  {
   "bugid": 1749183,
   "status": "RESOLVED",
   "component": "Core:Graphics: WebRender",
   "summary": "Nightly doesnt recover from manually \"trigger device reset\" in about:support"
  },
  {
   "bugid": 1748852,
   "status": "NEW",
   "component": "Core:IPC",
   "summary": "Add a MOZ_ASSERT_UNLESS_FUZZING to IPC_FAIL caused error path(s)"
  },
  {
   "bugid": 1712836,
   "status": "RESOLVED",
   "component": "Core:ImageLib",
   "summary": "Intermittent image/test/crashtests/1676172-1.html | load failed: timed out waiting for pending paint count to reach zero (waiting for updateCanvasPending)"
  },
  {
   "bugid": 1750475,
   "status": "RESOLVED",
   "component": "Core:ImageLib",
   "summary": "support quality parameter for webp encoding via canvas (toBlob, toDataURL)"
  },
  {
   "bugid": 1746090,
   "status": "ASSIGNED",
   "component": "Core:JavaScript: GC",
   "summary": "[hazards] Prevent false alarms when a refcounted variable goes out of scope when it can be proven to not Release"
  },
  {
   "bugid": 1750792,
   "status": "RESOLVED",
   "component": "Core:JavaScript: GC",
   "summary": "Add an abstraction for pointers to malloc-allocated structures containing GC thing pointers"
  },
  {
   "bugid": 1750927,
   "status": "RESOLVED",
   "component": "Core:Layout: Form Controls",
   "summary": "Fix non-unified-build bustage in layout/forms/nsCheckboxRadioFrame.h"
  },
  {
   "bugid": 1750211,
   "status": "RESOLVED",
   "component": "Core:Networking: HTTP",
   "summary": "Return error in unexpected state"
  },
  {
   "bugid": 1749017,
   "status": "RESOLVED",
   "component": "Core:Security: PSM",
   "summary": "client cert dialog is no longer displaying dates in validity period"
  },
  {
   "bugid": 1750089,
   "status": "RESOLVED",
   "component": "Core:Security: PSM",
   "summary": "avoid calling nsIX509Cert::GetCert()"
  },
  {
   "bugid": 1733054,
   "status": "RESOLVED",
   "component": "Core:Storage: Quota Manager",
   "summary": "Got an QuotaExceededError When my page's storage reach 5m"
  },
  {
   "bugid": 1751018,
   "status": "RESOLVED",
   "component": "Core:Web Painting",
   "summary": "Change FrameFlags to EnumSet"
  },
  {
   "bugid": 1749174,
   "status": "RESOLVED",
   "component": "Core:Widget: Gtk",
   "summary": "Consider enabling wayland if available"
  },
  {
   "bugid": 1746645,
   "status": "RESOLVED",
   "component": "Core:XPCOM",
   "summary": "Generate EscapeChars array programmatically"
  },
  {
   "bugid": 1749497,
   "status": "RESOLVED",
   "component": "Core:XPCOM",
   "summary": "Perma Late Beta Assertion failure: mSource == source (String was replaced!), at /builds/worker/checkouts/gecko/xpcom/io/nsStringStream.cpp when Gecko 97 switches to Late Beta on 2022-01-21"
  },
  {
   "bugid": 1737969,
   "status": "RESOLVED",
   "component": "DevTools:Debugger",
   "summary": "Remove lodash findIndex usage"
  },
  {
   "bugid": 1737986,
   "status": "RESOLVED",
   "component": "DevTools:Debugger",
   "summary": "Replace lodash throttle usage with devtools/shared/throttle"
  },
  {
   "bugid": 1750613,
   "status": "RESOLVED",
   "component": "DevTools:Debugger",
   "summary": "Rename `underRoot` function"
  },
  {
   "bugid": 1750227,
   "status": "RESOLVED",
   "component": "DevTools:Framework",
   "summary": "Ensure Browser Toolbox gets closed in tests using initBrowserToolboxTask"
  },
  {
   "bugid": 1571212,
   "status": "RESOLVED",
   "component": "DevTools:General",
   "summary": "Intermittent TEST-UNEXPECTED-TIMEOUT | devtools/server/tests/test_stepping-12.js | Test timed out"
  },
  {
   "bugid": 1750915,
   "status": "RESOLVED",
   "component": "DevTools:General",
   "summary": "[DevTools Release Tasks - Cycle 98] Remove backward compatibility code"
  },
  {
   "bugid": 1747429,
   "status": "RESOLVED",
   "component": "Firefox:Address Bar",
   "summary": "Remove preprocessor use of urlbar-related definitions"
  },
  {
   "bugid": 1749435,
   "status": "RESOLVED",
   "component": "Firefox:Bookmarks & History",
   "summary": "Use Fluent to localize `bookmarks.html` at run-time rather than interpolating localized strings at build-time"
  },
  {
   "bugid": 1750042,
   "status": "RESOLVED",
   "component": "Firefox:Downloads Panel",
   "summary": "Local file links download file instead of opening linked location"
  },
  {
   "bugid": 1750484,
   "status": "RESOLVED",
   "component": "Firefox:Downloads Panel",
   "summary": "\"Delete\" context menu should not remove the download history"
  },
  {
   "bugid": 1747181,
   "status": "RESOLVED",
   "component": "Firefox:Installer",
   "summary": "Remove LegalTrademarks from Windows installer"
  },
  {
   "bugid": 1731101,
   "status": "RESOLVED",
   "component": "Firefox:Messaging System",
   "summary": "PopupNotification doorhanger design polish: font, width should match the design of other notification-style panels"
  },
  {
   "bugid": 1750824,
   "status": "RESOLVED",
   "component": "Firefox:Pocket",
   "summary": "Save to Pocket refresh - scaffold style guide"
  },
  {
   "bugid": 1741554,
   "status": "RESOLVED",
   "component": "Firefox:Preferences",
   "summary": "Intermittent browser_connection_dnsoverhttps.js | application crashed [@ mozilla::net::nsSocketEvent::Run()] |  after FATAL ERROR: Non-local network connections are disabled and a connection attempt to mozilla.cloudflare-dns.com (104.16.248.249) was made."
  },
  {
   "bugid": 1748851,
   "status": "RESOLVED",
   "component": "Firefox:Security",
   "summary": "External protocol dialog does not account for opaque origin"
  },
  {
   "bugid": 1591040,
   "status": "ASSIGNED",
   "component": "Firefox:Toolbars and Customization",
   "summary": "Cannot active contextMenu on web extension icon when firefox is in fullscreen mode"
  },
  {
   "bugid": 1749386,
   "status": "RESOLVED",
   "component": "Firefox Build System:Bootstrap Configuration",
   "summary": "Bootstrap error with `fix_stacks` artifact | 400 Client Error: Bad Request"
  },
  {
   "bugid": 1750893,
   "status": "RESOLVED",
   "component": "Firefox Build System:General",
   "summary": "Move Android linker flags to python configure"
  },
  {
   "bugid": 1727819,
   "status": "RESOLVED",
   "component": "Firefox Build System:Mach Core",
   "summary": "Guard against risky virtualenv=>virtualenv activations"
  },
  {
   "bugid": 1750599,
   "status": "RESOLVED",
   "component": "Firefox Build System:Task Configuration",
   "summary": "High-frequency valgrind-test | Valgrind timed out (reached 2400 second limit)"
  },
  {
   "bugid": 1750842,
   "status": "RESOLVED",
   "component": "Firefox Build System:Task Configuration",
   "summary": "Add 'xorigin' to mozinfo guess in task configuration"
  },
  {
   "bugid": 1750855,
   "status": "RESOLVED",
   "component": "Firefox Build System:Task Configuration",
   "summary": "Perma valgrind-test | Valgrind timed out (reached 2400 second limit)"
  },
  {
   "bugid": 1750569,
   "status": "RESOLVED",
   "component": "GeckoView:General",
   "summary": "requestScreenPixels() never completes if GPU process is restarted whilst screenshot request is pending"
  },
  {
   "bugid": 1750756,
   "status": "RESOLVED",
   "component": "GeckoView:General",
   "summary": "test_telemetryController.js fails on Android with GPU process enabled"
  },
  {
   "bugid": 1750878,
   "status": "RESOLVED",
   "component": "GeckoView:General",
   "summary": "Forward onTrimMemory and onLowMemory to Gecko in main process"
  },
  {
   "bugid": 1750937,
   "status": "RESOLVED",
   "component": "GeckoView:General",
   "summary": "Tab focus may be lost when test_runner restarts activity"
  },
  {
   "bugid": 1750466,
   "status": "RESOLVED",
   "component": "Thunderbird:Upstream Synchronization",
   "summary": "Unwanted mailto: handlers added to Thunderbird by default"
  },
  {
   "bugid": 1750799,
   "status": "RESOLVED",
   "component": "Toolkit:Add-ons Manager",
   "summary": "VoiceOver announcement is confusing for add-on More Options menu"
  },
  {
   "bugid": 1749620,
   "status": "RESOLVED",
   "component": "Toolkit:Async Tooling",
   "summary": "Remove osfile.jsm from TerminatorTelemetry.jsm"
  },
  {
   "bugid": 1750968,
   "status": "VERIFIED",
   "component": "Toolkit:FeatureGate",
   "summary": "Perma TEST-UNEXPECTED-FAIL | toolkit/components/featuregates/test/unit/test_FeatureGate.js | testAllDefaultsMatchSettings - [testAllDefaultsMatchSettings : 440] Feature devtools.inspector.compatibility.enabled  when Gecko 98 merges to Beta"
  },
  {
   "bugid": 1747461,
   "status": "RESOLVED",
   "component": "Toolkit:OS.File",
   "summary": "Remove FileUtils.getFile from browser/"
  },
  {
   "bugid": 1670108,
   "status": "RESOLVED",
   "component": "Toolkit:Picture-in-Picture",
   "summary": "Create infrastructure for site-specific video player adapters"
  },
  {
   "bugid": 1746841,
   "status": "RESOLVED",
   "component": "WebExtensions:Frontend",
   "summary": "moz-extension:// CSS urls cached across addon reloads and updates"
  }
 ],
 "fixed": 61,
 "total": 67,
 "restricted": 2
}