{
 "date": "2023-07-14",
 "buildid": "20230714094120",
 "cset": "196cda3a105202c8969a926a0637db0e0014c07d",
 "bugs": [
  {
   "bugid": 1814588,
   "status": "RESOLVED",
   "component": "Core:CSS Parsing and Computation",
   "summary": "[css-values-4] Sign-Related Functions: abs() and sign()"
  },
  {
   "bugid": 1815448,
   "status": "RESOLVED",
   "component": "Core:CSS Parsing and Computation",
   "summary": "Add a product node to calc() to allow multiplication with nodes that are not distributive"
  },
  {
   "bugid": 1840781,
   "status": "RESOLVED",
   "component": "Core:CSS Parsing and Computation",
   "summary": "[css-nesting] Ship CSS Nesting"
  },
  {
   "bugid": 1843349,
   "status": "RESOLVED",
   "component": "Core:CSS Parsing and Computation",
   "summary": "[css-nesting] Fix tests to account for recent resolutions."
  },
  {
   "bugid": 1685333,
   "status": "RESOLVED",
   "component": "Core:DOM: Core & HTML",
   "summary": "Calling appendChild with ShadowRoot to iframe document throws HierarchyRequestError"
  },
  {
   "bugid": 1778112,
   "status": "RESOLVED",
   "component": "Core:DOM: Core & HTML",
   "summary": "Move DOM code to use mjs files, rather than defining sourceType for ESLint"
  },
  {
   "bugid": 1842007,
   "status": "ASSIGNED",
   "component": "Core:DOM: Core & HTML",
   "summary": "Replace DomPromiseListener uses with Promise::ThenCatchWithCycleCollectedArgs"
  },
  {
   "bugid": 1842792,
   "status": "RESOLVED",
   "component": "Core:DOM: Core & HTML",
   "summary": "Shipping <link rel=\"modulepreload\"> causes breakage in some(?) ImportMap usage"
  },
  {
   "bugid": 1843159,
   "status": "RESOLVED",
   "component": "Core:DOM: Core & HTML",
   "summary": "Reduce the number of virtual calls calling Location::GetHash triggers"
  },
  {
   "bugid": 1843277,
   "status": "RESOLVED",
   "component": "Core:DOM: Core & HTML",
   "summary": "Remove nsContentUtils::HasPluginWithUncontrolledEventDispatch."
  },
  {
   "bugid": 1843279,
   "status": "NEW",
   "component": "Core:DOM: Core & HTML",
   "summary": "Simplify IsInFocusedTab."
  },
  {
   "bugid": 1550792,
   "status": "RESOLVED",
   "component": "Core:DOM: Security",
   "summary": "Consider changing LoadInfo::LoadInfo to use IsSecureContext and !IsPotentiallyTrustworthyLoopbackURL"
  },
  {
   "bugid": 1841689,
   "status": "RESOLVED",
   "component": "Core:DOM: UI Events & Focus Handling",
   "summary": "Assertion failure: IsValid(), at /builds/worker/checkouts/gecko/widget/ContentCache.cpp:235"
  },
  {
   "bugid": 1838123,
   "status": "RESOLVED",
   "component": "Core:Disability Access APIs",
   "summary": "UIA client detection is broken"
  },
  {
   "bugid": 1838250,
   "status": "RESOLVED",
   "component": "Core:Disability Access APIs",
   "summary": "High CPU usage and unresponsiveness on page with very long horizontal scroll"
  },
  {
   "bugid": 1842160,
   "status": "RESOLVED",
   "component": "Core:Disability Access APIs",
   "summary": "Missing labelled-by, label-for relationship with figures and their captions"
  },
  {
   "bugid": 1841728,
   "status": "RESOLVED",
   "component": "Core:Graphics",
   "summary": "Change the parameter types of BaseMargin::SizeTo() to Coord"
  },
  {
   "bugid": 1843143,
   "status": "RESOLVED",
   "component": "Core:Graphics: Canvas2D",
   "summary": "Update aa-stroke to improve handling of round joins"
  },
  {
   "bugid": 1843021,
   "status": "RESOLVED",
   "component": "Core:Graphics: WebGPU",
   "summary": "Frequent CTS intermittent crashes in StatelessTracker::remove_abandoned"
  },
  {
   "bugid": 1836063,
   "status": "RESOLVED",
   "component": "Core:Graphics: WebRender",
   "summary": "Poor performance with translucent rounded-rectangles with box shadows"
  },
  {
   "bugid": 1842345,
   "status": "RESOLVED",
   "component": "Core:Graphics: WebRender",
   "summary": "Remove gfx.webrender.enabled pref"
  },
  {
   "bugid": 1842447,
   "status": "RESOLVED",
   "component": "Core:Graphics: WebRender",
   "summary": "[sw-wr] with DPI=1.5, rendering artifact on a radial gradient demo"
  },
  {
   "bugid": 1842857,
   "status": "RESOLVED",
   "component": "Core:Graphics: WebRender",
   "summary": "Perma REFTEST TEST-UNEXPECTED-FAIL | layout/reftests/pixel-rounding/border-image-width-4.html == layout/reftests/pixel-rounding/border-image-width-0.html | image comparison, max difference: 112, number of differing pixels: 21 when Gecko 117 merges to Beta"
  },
  {
   "bugid": 1839598,
   "status": "RESOLVED",
   "component": "Core:JavaScript: WebAssembly",
   "summary": "Fast-track allocation of WasmStructObjects that have no OOL storage"
  },
  {
   "bugid": 1842952,
   "status": "RESOLVED",
   "component": "Core:Layout",
   "summary": "Perma [tier 2] transform-3d/1157984-1.html != about:blank | image comparison, max difference: 0, number of differing pixels: 0"
  },
  {
   "bugid": 1843086,
   "status": "RESOLVED",
   "component": "Core:Layout: Tables",
   "summary": "baseline-source completely breaks tables"
  },
  {
   "bugid": 1842651,
   "status": "RESOLVED",
   "component": "Core:Networking",
   "summary": "Frequent Android xpcshell [taskcluster:error] Task timeout after 5400 seconds. Force killing container."
  },
  {
   "bugid": 1843119,
   "status": "RESOLVED",
   "component": "Core:Networking",
   "summary": "Remove SpinEventLoopUntil from WifiMonitor"
  },
  {
   "bugid": 1748138,
   "status": "RESOLVED",
   "component": "Core:Privacy: Anti-Tracking",
   "summary": "image file size in image info dialog is unknown with top-level site partitioning"
  },
  {
   "bugid": 1830058,
   "status": "RESOLVED",
   "component": "Core:Privacy: Anti-Tracking",
   "summary": "Extend query_stripping_count_by_param to account for updated query strip list"
  },
  {
   "bugid": 1836248,
   "status": "RESOLVED",
   "component": "Core:Privacy: Anti-Tracking",
   "summary": "Extend the current query stripping code to support the strip-on-share strip list"
  },
  {
   "bugid": 825254,
   "status": "RESOLVED",
   "component": "Core:SVG",
   "summary": "SMIL animateMotion fails to stay on path when the path itself is SMIL-animated"
  },
  {
   "bugid": 1840871,
   "status": "RESOLVED",
   "component": "Core:Security",
   "summary": "Crash in DetectJSHacks in subprocesses"
  },
  {
   "bugid": 1840545,
   "status": "RESOLVED",
   "component": "Core:Storage: Quota Manager",
   "summary": "Move all code related to origin operations to separate source files"
  },
  {
   "bugid": 1840770,
   "status": "RESOLVED",
   "component": "Core:Storage: Quota Manager",
   "summary": "Move PQuotaParent implementation to separate source files"
  },
  {
   "bugid": 1707735,
   "status": "REOPENED",
   "component": "Core:WebRTC",
   "summary": "14 tests skipped on apple_silicon"
  },
  {
   "bugid": 1842298,
   "status": "RESOLVED",
   "component": "Core:WebRTC",
   "summary": "improve bootstrapping of elm_rebase.sh"
  },
  {
   "bugid": 1843217,
   "status": "RESOLVED",
   "component": "Core:WebRTC",
   "summary": "remove deprecated use of webrtc::WebRtcKeyValueConfig in favor of webrtc::FieldTrialsView"
  },
  {
   "bugid": 1843261,
   "status": "ASSIGNED",
   "component": "Core:Widget",
   "summary": "Remove browser.tabs.remote.desktopbehavior pref"
  },
  {
   "bugid": 1834629,
   "status": "ASSIGNED",
   "component": "Core:XPCOM",
   "summary": "Notify the background main thread of QoS changes from another thread"
  },
  {
   "bugid": 1840959,
   "status": "RESOLVED",
   "component": "Core:XPCOM",
   "summary": "Use after free in xpcom/string/nsTSubstring.cpp"
  },
  {
   "bugid": 1822310,
   "status": "ASSIGNED",
   "component": "DevTools:Debugger",
   "summary": "Revise \"cx\"/context \"threadcx\"/thread context assertion in the debugger"
  },
  {
   "bugid": 1824653,
   "status": "RESOLVED",
   "component": "DevTools:Inspector",
   "summary": "Expanded computed view shows erroneous information with @layer"
  },
  {
   "bugid": 1841971,
   "status": "RESOLVED",
   "component": "DevTools:Inspector: Rules",
   "summary": "Rule view only displays closest @import layer/condition"
  },
  {
   "bugid": 1842157,
   "status": "RESOLVED",
   "component": "DevTools:Inspector: Rules",
   "summary": "[Inactive CSS] Report ignored properties on highlight pseudo-elements"
  },
  {
   "bugid": 1843074,
   "status": "RESOLVED",
   "component": "Firefox:Address Bar",
   "summary": "SkippableTimer.done should be set immediately"
  },
  {
   "bugid": 1843186,
   "status": "RESOLVED",
   "component": "Firefox:Address Bar",
   "summary": "Append UTM parameters to Pocket Collection URLs"
  },
  {
   "bugid": 1840269,
   "status": "RESOLVED",
   "component": "Firefox:File Handling",
   "summary": "[Linux] Double quotes sometimes kept, sometimes removed, depending on file extension"
  },
  {
   "bugid": 1826588,
   "status": "RESOLVED",
   "component": "Firefox:Messaging System",
   "summary": "Add FeatureCallout to newtab"
  },
  {
   "bugid": 1840517,
   "status": "NEW",
   "component": "Firefox:Messaging System",
   "summary": "Build Addons picker screen for about:welcome"
  },
  {
   "bugid": 1842605,
   "status": "RESOLVED",
   "component": "Firefox:Migration",
   "summary": "[macOS] Infinite loading when importing an invalid or empty .csv file by using the Safari browser option"
  },
  {
   "bugid": 1843175,
   "status": "RESOLVED",
   "component": "Firefox:New Tab Page",
   "summary": "TopSitesFeed: Failed to fetch data from Contile server: cacheHeader is null"
  },
  {
   "bugid": 1843273,
   "status": "RESOLVED",
   "component": "Firefox:PDF Viewer",
   "summary": "Update PDF.js to new version 762d86a59ebd7cc2f7733f519de70610089344e6 from 2023-07-12 19:44:34"
  },
  {
   "bugid": 1841086,
   "status": "RESOLVED",
   "component": "Firefox:Shopping",
   "summary": "Page parent component to connect API data to UI components"
  },
  {
   "bugid": 1839520,
   "status": "RESOLVED",
   "component": "Firefox:Sync",
   "summary": "Convert tps.jsm to an ES module"
  },
  {
   "bugid": 1843219,
   "status": "RESOLVED",
   "component": "Firefox Build System:Bootstrap Configuration",
   "summary": "Perma [tier 2] bootstrap opensuse-tumbleweed subprocess.CalledProcessError: Command '('lsb_release', '-a')' returned non-zero exit status 2."
  },
  {
   "bugid": 1842918,
   "status": "RESOLVED",
   "component": "Firefox Build System:General",
   "summary": "Makefiles can't handle Python executable in paths with spaces"
  },
  {
   "bugid": 1843012,
   "status": "RESOLVED",
   "component": "Firefox Build System:General",
   "summary": "Do not use PGO_CFLAGS where PGO_LDFLAGS is expected"
  },
  {
   "bugid": 1695312,
   "status": "NEW",
   "component": "Firefox Build System:Mach Core",
   "summary": "Make mach command modules be loaded selectively"
  },
  {
   "bugid": 1808732,
   "status": "ASSIGNED",
   "component": "Firefox Build System:Mach Core",
   "summary": "Move vendored packages out of the `mach` site"
  },
  {
   "bugid": 1842700,
   "status": "ASSIGNED",
   "component": "Firefox Build System:Mach Core",
   "summary": "l10n-cross-channel MachCommandReference uses wrong module path"
  },
  {
   "bugid": 1843026,
   "status": "RESOLVED",
   "component": "Firefox Build System:Task Configuration",
   "summary": "Use taskcluster-built python for condprof task"
  },
  {
   "bugid": 1837000,
   "status": "ASSIGNED",
   "component": "Release Engineering:Firefox-CI Administration",
   "summary": "SpiderMonkey tasks and PGO builds crash when subsystem version is bumped to 10.0"
  },
  {
   "bugid": 1838664,
   "status": "RESOLVED",
   "component": "Remote Protocol:WebDriver BiDi",
   "summary": "Implement \"browsingContext.setViewport\" command"
  },
  {
   "bugid": 1837075,
   "status": "RESOLVED",
   "component": "WebExtensions:General",
   "summary": "Consistent error handling in NativeManifests _tryPaths & NativeManifests.lookupManifest"
  }
 ],
 "fixed": 54,
 "total": 65,
 "restricted": 3
}