{
 "bugs": [
  {
   "bugid": "1667533",
   "status": "RESOLVED",
   "component": "Core:Audio/Video: Recording",
   "summary": "Perma [android] TEST-UNEXPECTED-TIMEOUT | /mediacapture-record/MediaRecorder-peerconnection.https.html | TestRunner hit external timeout (this may indicate a hang When Gecko 83 merges to Beta on 2020-10-19"
  },
  {
   "bugid": "1668577",
   "status": "RESOLVED",
   "component": "Core:DOM: Navigation",
   "summary": "Make child process to send offset to parent process, not index"
  },
  {
   "bugid": "1662839",
   "status": "ASSIGNED",
   "component": "Core:Layout",
   "summary": "Move AuthorStyleDisabled/HintCharset/HintCharsetSource to WindowContext or BrowsingContext"
  },
  {
   "bugid": "1668421",
   "status": "RESOLVED",
   "component": "Core:MFBT",
   "summary": "fallible example code in comment is incorrect"
  },
  {
   "bugid": "1668966",
   "status": "RESOLVED",
   "component": "Core:Panning and Zooming",
   "summary": "only clear PresShell::mResolutionUpdated after the apz transaction"
  },
  {
   "bugid": "1667612",
   "status": "RESOLVED",
   "component": "Core:Panning and Zooming",
   "summary": "factor waitToClearOutAnyPotentialScrolls out from various tests and put it in apz_test_utils.js"
  },
  {
   "bugid": "1667116",
   "status": "RESOLVED",
   "component": "Core:Widget: Gtk",
   "summary": "Screen tearing in full screen"
  },
  {
   "bugid": "1668430",
   "status": "RESOLVED",
   "component": "Firefox:Address Bar",
   "summary": "Add test about search mode and one-off button behavior when typing search engine alias after selecting one of one-off button."
  },
  {
   "bugid": "1668052",
   "status": "RESOLVED",
   "component": "Firefox:Session Restore",
   "summary": "Pass the BrowserParent's browsing context to UpdateSessionStore instead of getting it from the frame element's frameloader."
  },
  {
   "bugid": "1662319",
   "status": "RESOLVED",
   "component": "Firefox:Sync",
   "summary": "Remove the sync engine \"repairers\""
  },
  {
   "bugid": "1667841",
   "status": "RESOLVED",
   "component": "Firefox Build System:Toolchains",
   "summary": "Update revert-r362047-and-r362065.patch for clang-12"
  }
 ],
 "date": "2020-10-05",
 "cset": "5380e007a12cb5081a14736d7e00885c57f42129",
 "buildid": "20201005093214",
 "fixed": 10,
 "total": 11,
 "restricted": null
}