{
 "date": "2025-08-03",
 "buildid": "20250803092620",
 "cset": "9065fcd9ed3ad00695c1d3dc8bf9dc48d875d0ed",
 "bugs": [
  {
   "bugid": 1980649,
   "status": "ASSIGNED",
   "component": "Core:Audio/Video",
   "summary": "Always reconfigure codec support after a gfxVar change"
  },
  {
   "bugid": 1980247,
   "status": "RESOLVED",
   "component": "Core:Audio/Video: Web Codecs",
   "summary": "Crash when running async HW encoder on Windows"
  },
  {
   "bugid": 1980259,
   "status": "RESOLVED",
   "component": "Core:DOM: Selection",
   "summary": "Crash in [@ stackoverflow | SelectionDetails::~SelectionDetails]"
  },
  {
   "bugid": 1980267,
   "status": "RESOLVED",
   "component": "Core:SVG",
   "summary": "Assertion failure: viewbox.width > 0.0f && viewbox.height > 0.0f (Rendering should be disabled), at /builds/worker/checkouts/gecko/dom/svg/SVGMarkerElement.cpp:199"
  },
  {
   "bugid": 1980596,
   "status": "RESOLVED",
   "component": "Core:SVG",
   "summary": "SVGPathElement.setPathData() method swaps <arc-flag> and <sweep-flag> values"
  },
  {
   "bugid": 1978911,
   "status": "RESOLVED",
   "component": "Core:Widget: Gtk",
   "summary": "[NVIDIA 560.35.03] Instant crash of 141.0 on RHEL 9.4"
  },
  {
   "bugid": 1980773,
   "status": "RESOLVED",
   "component": "Toolkit:UI Widgets",
   "summary": "Fix back button context menu favicons."
  },
  {
   "bugid": 1971013,
   "status": "RESOLVED",
   "component": "WebExtensions:General",
   "summary": "Implement test.onTestStarted and onTestFinished"
  }
 ],
 "fixed": 7,
 "total": 8,
 "restricted": 0
}