{
 "date": "2025-10-06",
 "buildid": "20251006095753",
 "cset": "c8f9e8584155d95a1d44eb7fba91d39c22941aa0",
 "bugs": [
  {
   "bugid": 1992551,
   "status": "RESOLVED",
   "component": "Core:DOM: Editor",
   "summary": "Simplify text editor value getter."
  },
  {
   "bugid": 1992503,
   "status": "RESOLVED",
   "component": "Core:DOM: Navigation",
   "summary": "Recreating contiguous session history entry list after session restore needs to consider entries whose parent entries are same-document equivalent"
  },
  {
   "bugid": 1980264,
   "status": "RESOLVED",
   "component": "Core:Graphics: Canvas2D",
   "summary": "Canvas randomization is too slow"
  },
  {
   "bugid": 1991689,
   "status": "RESOLVED",
   "component": "Core:Layout: Text and Fonts",
   "summary": "1167.55 - 5.17% perf_reftest_singletons svg-text-textLength-1.html / perf_reftest_singletons thai-reflow.html + 10 more (Linux, OSX, Windows) regression on Tue September 23 2025"
  },
  {
   "bugid": 1992581,
   "status": "RESOLVED",
   "component": "Core:Widget: Gtk",
   "summary": "[Linux] Clear mHasReceivedSizeAllocate on nsWindow::OnUnmap()"
  },
  {
   "bugid": 1990108,
   "status": "RESOLVED",
   "component": "Firefox Build System:General",
   "summary": "Update ohttp and bhttp crates to git rev bf6a983845cc0b540effb3a615e92d914dfcfd0b"
  },
  {
   "bugid": 1991831,
   "status": "RESOLVED",
   "component": "Toolkit:Telemetry",
   "summary": "Harden telemetry observer registration/removal"
  }
 ],
 "fixed": 7,
 "total": 7,
 "restricted": 0
}