{
 "date": "2022-11-20",
 "buildid": "20221120092051",
 "cset": "46dae1c56dade459258373ddfed526da69c68c49",
 "bugs": [
  {
   "bugid": 1800979,
   "status": "RESOLVED",
   "component": "Core:CSS Parsing and Computation",
   "summary": "Sprite sheet images not loading properly on first page-load at m.vlive.tv"
  },
  {
   "bugid": 1709184,
   "status": "REOPENED",
   "component": "Core:DOM: Core & HTML",
   "summary": "Intermittent Assertion failure: false (ClearOnShutdown for phase that already was cleared), at /builds/worker/checkouts/gecko/xpcom/base/ClearOnShutdown.cpp:20"
  },
  {
   "bugid": 1801380,
   "status": "RESOLVED",
   "component": "Core:DOM: Core & HTML",
   "summary": "Assertion failure: !aElement->HasDirAuto() (RecomputeDirectionality called with dir=auto), at /builds/worker/checkouts/gecko/dom/base/DirectionalityUtils.cpp:680"
  },
  {
   "bugid": 1801433,
   "status": "RESOLVED",
   "component": "Core:Disability Access APIs",
   "summary": "Cleanup: Remove PresShell::GetAccessibilityService/IsAccessibilityActive"
  },
  {
   "bugid": 1799707,
   "status": "RESOLVED",
   "component": "Core:Layout: Grid",
   "summary": "Cleanup ResolveIntrinsicSize function with better naming"
  },
  {
   "bugid": 1781960,
   "status": "RESOLVED",
   "component": "Core:Panning and Zooming",
   "summary": "stop doing (reflow) zoom when ctrl/cmd plus touchpad scroll on mac"
  },
  {
   "bugid": 1768581,
   "status": "ASSIGNED",
   "component": "Core:XPCOM",
   "summary": "Verify if we can have a different order inside AppShutdown:.AdvanceShutdownPhaseInternal"
  },
  {
   "bugid": 1510561,
   "status": "RESOLVED",
   "component": "Developer Infrastructure:Lint and Formatting",
   "summary": "Investigate switching to eslint-plugin-jsdoc"
  },
  {
   "bugid": 1801138,
   "status": "RESOLVED",
   "component": "Firefox:Theme",
   "summary": "Drop-down menus items with empty values have a smaller height compared to the ones that have values"
  }
 ],
 "fixed": 7,
 "total": 9,
 "restricted": 1
}