{
 "date": "2025-07-25",
 "buildid": "20250725093757",
 "cset": "12bf685e70030752d8724ade6d210e6f68646c59",
 "bugs": [
  {
   "bugid": 1977959,
   "status": "RESOLVED",
   "component": "Core:Audio/Video",
   "summary": "Intermittent application crashed [@ nsDefaultComparator<AVCodecID,AVCodecID>::Equals] | single tracking bug"
  },
  {
   "bugid": 1978942,
   "status": "RESOLVED",
   "component": "Core:Audio/Video",
   "summary": "[wmfme] Hook up the session close properly for MFCDMSession"
  },
  {
   "bugid": 1979078,
   "status": "RESOLVED",
   "component": "Core:Audio/Video",
   "summary": "Crash in [@ IPC::ParamTraits<mozilla::EncoderConfig>::Write | mozilla::PRemoteMediaManagerChild::SendPRemoteEncoderConstructor]"
  },
  {
   "bugid": 1978544,
   "status": "RESOLVED",
   "component": "Core:Audio/Video: Playback",
   "summary": "Move HTMLMediaElement files from dom/html to a dom/media subdirectory"
  },
  {
   "bugid": 1978684,
   "status": "RESOLVED",
   "component": "Core:Audio/Video: Playback",
   "summary": "Crash in  [@ Microsoft::WRL::ComPtr<T>::operator int Microsoft::WRL::Details::BoolStruct::* ]"
  },
  {
   "bugid": 1978970,
   "status": "RESOLVED",
   "component": "Core:Audio/Video: Playback",
   "summary": "Update opus to new version f92fdda4f9b75ecb5f0f38b86c991195585579ea from 2025-07-23 17:03:38"
  },
  {
   "bugid": 1978976,
   "status": "RESOLVED",
   "component": "Core:DOM: Navigation",
   "summary": "Crash in [@ mozilla::dom::RangeBasedTextDirectiveCreator::FindAllMatchingCandidates]"
  },
  {
   "bugid": 1978250,
   "status": "RESOLVED",
   "component": "Core:Gecko Profiler",
   "summary": "Add tests for simple payload markers"
  },
  {
   "bugid": 1979112,
   "status": "RESOLVED",
   "component": "Core:Graphics: CanvasWebGL",
   "summary": "Crash in [@ mozilla::webgl::TexUnpackSurface::BlitSd]"
  },
  {
   "bugid": 1978256,
   "status": "RESOLVED",
   "component": "Core:Graphics: Text",
   "summary": "Update harfbuzz to new version 11.3.2 from 2025-07-20 18:12:39"
  },
  {
   "bugid": 1960399,
   "status": "RESOLVED",
   "component": "Core:Graphics: WebGPU",
   "summary": "`GPUDevice.createRenderPipelineAsync` and `GPUDevice.createComputePipelineAsync` do not return `GPUPipelineError`s"
  },
  {
   "bugid": 1975714,
   "status": "ASSIGNED",
   "component": "Core:Graphics: WebGPU",
   "summary": "Message queueing follow-ups"
  },
  {
   "bugid": 1977861,
   "status": "RESOLVED",
   "component": "Core:Graphics: WebGPU",
   "summary": "Stop leaking BGLs returned by GPUPipelineBase.getBindGroupLayout()"
  },
  {
   "bugid": 1978369,
   "status": "RESOLVED",
   "component": "Core:Graphics: WebGPU",
   "summary": "Stop leaking queues"
  },
  {
   "bugid": 1761993,
   "status": "RESOLVED",
   "component": "Core:JavaScript Engine",
   "summary": "Handle broken promises in AsyncGenerator.prototype.return"
  },
  {
   "bugid": 1978783,
   "status": "RESOLVED",
   "component": "Core:JavaScript Engine: JIT",
   "summary": "Split tryAttachTypedArrayConstructor into separate methods for each argument kind"
  },
  {
   "bugid": 1978800,
   "status": "RESOLVED",
   "component": "Core:JavaScript Engine: JIT",
   "summary": "Add convenience functions to MMinMax when \"isMax\" argument is a constant"
  },
  {
   "bugid": 1978996,
   "status": "RESOLVED",
   "component": "Core:JavaScript Engine: JIT",
   "summary": "riscv64-simulator: \"Error: Assertion failed: got 0, expected 5\" in asm.js/testZOOB.js"
  },
  {
   "bugid": 1978641,
   "status": "RESOLVED",
   "component": "Core:JavaScript: WebAssembly",
   "summary": "Update about:memory accounting for wasm GC objects"
  },
  {
   "bugid": 1978929,
   "status": "RESOLVED",
   "component": "Core:Layout: Grid",
   "summary": "Remove nsLayoutUtils::MIN_INTRINSIC_ISIZE"
  },
  {
   "bugid": 1978472,
   "status": "NEW",
   "component": "Core:Machine Learning",
   "summary": "Page Buddy Feature Foundation"
  },
  {
   "bugid": 1978921,
   "status": "RESOLVED",
   "component": "Core:Machine Learning",
   "summary": "pref on smart tab grouping by default while restricting to en-*"
  },
  {
   "bugid": 1931193,
   "status": "RESOLVED",
   "component": "Core:MathML",
   "summary": "MANIFEST testing/web-platform/meta/mathml/presentation-markup/spaces/space-like-003.html.ini"
  },
  {
   "bugid": 1976964,
   "status": "RESOLVED",
   "component": "Core:Networking: DNS",
   "summary": "Fenix: DoH performance degrades under high concurrent request load"
  },
  {
   "bugid": 1978814,
   "status": "RESOLVED",
   "component": "Core:Networking: DNS",
   "summary": "Record the count of network change event"
  },
  {
   "bugid": 1977673,
   "status": "RESOLVED",
   "component": "Core:Performance: General",
   "summary": "PerfStats beyond the first 32 are not collected on Android/CI"
  },
  {
   "bugid": 1979147,
   "status": "RESOLVED",
   "component": "Core:Privacy: Anti-Tracking",
   "summary": "Add `privacy.trackingprotection.allow_list.baseline.enabled` to `SpeicalMessageActions.setPref`"
  },
  {
   "bugid": 1978566,
   "status": "RESOLVED",
   "component": "Core:SVG",
   "summary": "Fix objectBoundingBox with font relative units"
  },
  {
   "bugid": 1971027,
   "status": "RESOLVED",
   "component": "Core:Security: PSM",
   "summary": "about:profiles requires primary password"
  },
  {
   "bugid": 1937025,
   "status": "RESOLVED",
   "component": "Core:Security: Process Sandboxing",
   "summary": "Update security/sandbox/chromium/ to Chromium commit 6d3cc0dac5057925e096b1329680124b19f35842"
  },
  {
   "bugid": 1975578,
   "status": "RESOLVED",
   "component": "Core:Widget: Gtk",
   "summary": "Crash in [@ mozilla::SystemTimeConverter<T>::IsTimeNewerThanTimestamp]"
  },
  {
   "bugid": 1829610,
   "status": "RESOLVED",
   "component": "DevTools:Debugger",
   "summary": "Spending most of the time computing original source URLs in the source-map worker"
  },
  {
   "bugid": 1978864,
   "status": "RESOLVED",
   "component": "DevTools:Documentation",
   "summary": "Add documentation for the paused overlay setting"
  },
  {
   "bugid": 1978538,
   "status": "RESOLVED",
   "component": "DevTools:Memory",
   "summary": "Window splitter in Devtools > Memory > Retaining Paths graph detects cursor position incorrectly"
  },
  {
   "bugid": 1977995,
   "status": "RESOLVED",
   "component": "Developer Infrastructure:Try",
   "summary": "Stop showing misleading estimates in the `mach try` terminal output"
  },
  {
   "bugid": 1975636,
   "status": "RESOLVED",
   "component": "Firefox:Address Bar",
   "summary": "TIP type result uses rich suggestion template"
  },
  {
   "bugid": 1978283,
   "status": "RESOLVED",
   "component": "Firefox:Address Bar",
   "summary": "results panel briefly flickers more than 10 results"
  },
  {
   "bugid": 1975799,
   "status": "ASSIGNED",
   "component": "Firefox:IP Protection",
   "summary": "IP Protection Panel cannot be accessed and focused on with the keyboard"
  },
  {
   "bugid": 1976022,
   "status": "ASSIGNED",
   "component": "Firefox:IP Protection",
   "summary": "Create a GuardianClient.sys.mjs"
  },
  {
   "bugid": 1978486,
   "status": "RESOLVED",
   "component": "Firefox:IP Protection",
   "summary": "Combine IP Protection panel custom elements"
  },
  {
   "bugid": 1968279,
   "status": "ASSIGNED",
   "component": "Firefox:Installer",
   "summary": "Firefox install link on new Windows 11 devices"
  },
  {
   "bugid": 1974083,
   "status": "RESOLVED",
   "component": "Firefox:Messaging System",
   "summary": "Add activeNotifications targeting test"
  },
  {
   "bugid": 1979210,
   "status": "RESOLVED",
   "component": "Firefox:New Tab Page",
   "summary": "Timer widget - persist redux state in cache"
  },
  {
   "bugid": 1973763,
   "status": "RESOLVED",
   "component": "Firefox:Search",
   "summary": "Add partner codes for distributions to search-config-v2 and search-telemetry-v2"
  },
  {
   "bugid": 1979121,
   "status": "RESOLVED",
   "component": "Firefox:Search",
   "summary": "Perma browser/components/search/test/unit/test_urlTelemetry.js - browser.search.content.unknown must be recorded. - false == true"
  },
  {
   "bugid": 1974880,
   "status": "RESOLVED",
   "component": "Firefox:Shell Integration",
   "summary": "Remove deleted Windows shortcuts from the uninstall log as they are deleted"
  },
  {
   "bugid": 1976020,
   "status": "RESOLVED",
   "component": "Firefox:Shell Integration",
   "summary": "Remove nsIWindowsShellService.getTaskbarTabShortcutPath and nsIWindowsShellService.getTaskbarTabPins"
  },
  {
   "bugid": 1977003,
   "status": "REOPENED",
   "component": "Firefox:Shell Integration",
   "summary": "Taskbar Tab windows display a Firefox icon when tasbkar windows are ungrouped"
  },
  {
   "bugid": 1977504,
   "status": "REOPENED",
   "component": "Firefox:Shell Integration",
   "summary": "Taskbar Tab reconstruction from shortcut is broken"
  },
  {
   "bugid": 1978130,
   "status": "RESOLVED",
   "component": "Firefox:Shell Integration",
   "summary": "browser/components/shell/test/createWindowsShortcut.js writes to the user's real desktop and Start menu folder"
  },
  {
   "bugid": 1978191,
   "status": "REOPENED",
   "component": "Firefox:Shell Integration",
   "summary": "test_taskbarTabs_pin.js tests are broken."
  },
  {
   "bugid": 1978950,
   "status": "ASSIGNED",
   "component": "Firefox:Shell Integration",
   "summary": "Taskbar Tabs leak memory during image container retrieval."
  },
  {
   "bugid": 1944719,
   "status": "RESOLVED",
   "component": "Firefox:Sidebar",
   "summary": "Sidebar extensions should be unpinnable from the launcher"
  },
  {
   "bugid": 1978083,
   "status": "RESOLVED",
   "component": "Firefox:Sidebar",
   "summary": "Increase pinned tab interaction cue size and display when within a pinned tab's distance"
  },
  {
   "bugid": 1968439,
   "status": "RESOLVED",
   "component": "Firefox:Tabbed Browser",
   "summary": "Make Ctrl+Tab panel work fine when constrained."
  },
  {
   "bugid": 1976026,
   "status": "RESOLVED",
   "component": "Firefox:Tabbed Browser",
   "summary": "AsyncTabSwitcher._useDumpForLogging triggers test failures on try"
  },
  {
   "bugid": 1978679,
   "status": "RESOLVED",
   "component": "Firefox:Tabbed Browser",
   "summary": "Dragging tab group from the last position makes it stuck on left edge"
  },
  {
   "bugid": 1950584,
   "status": "ASSIGNED",
   "component": "Firefox Build System:General",
   "summary": "Windows build creates flag_check.exe and flag_check.ilk in mozglue/static/rust/ and gfx/wr/swgl/ - should be in $objdir/$rust_target/{release,debug}/build/*/out"
  },
  {
   "bugid": 1920227,
   "status": "NEW",
   "component": "Firefox Build System:Mach Core",
   "summary": "`mach xpcshell` does not find libxul.so"
  },
  {
   "bugid": 1969980,
   "status": "ASSIGNED",
   "component": "Firefox for Android:General",
   "summary": "Remove 24 snackbars marked for removal"
  },
  {
   "bugid": 1977303,
   "status": "RESOLVED",
   "component": "Firefox for Android:General",
   "summary": "Crash in [@ android.util.AndroidRuntimeException: at com.android.internal.policy.PhoneWindow.requestFeature(PhoneWindow.java)]"
  },
  {
   "bugid": 1966977,
   "status": "RESOLVED",
   "component": "Firefox for Android:Performance",
   "summary": "Update visual completeness queue to use real indicators"
  },
  {
   "bugid": 1971317,
   "status": "RESOLVED",
   "component": "Firefox for Android:Performance",
   "summary": "Baseline Profile : Enable Baseline Profile generation for Onboarding"
  },
  {
   "bugid": 1971318,
   "status": "RESOLVED",
   "component": "Firefox for Android:Performance",
   "summary": "Baseline Profile: Break down the currently existing Browser CUJ into smaller scenarios"
  },
  {
   "bugid": 1979123,
   "status": "RESOLVED",
   "component": "Firefox for Android:Performance",
   "summary": "Intermittent org.mozilla.fenix.benchmark.baselineprofile.SwitchTabsBaselineProfileGenerator#generateBaselineProfile | androidx.test.uiautomator.UiObjectNotFoundException: UiSelector[RESOURCE_ID=org.mozilla.fenix:id/counter_box]"
  },
  {
   "bugid": 1947548,
   "status": "RESOLVED",
   "component": "Firefox for Android:Settings",
   "summary": "Implement the accessibility requirements for Unified Trust Panel"
  },
  {
   "bugid": 1955884,
   "status": "RESOLVED",
   "component": "Firefox for Android:Settings",
   "summary": "[app icon picker] Create an Util class that will change the enabled state of activity aliases"
  },
  {
   "bugid": 1955886,
   "status": "RESOLVED",
   "component": "Firefox for Android:Settings",
   "summary": "[app icon picker] Add app icon repository"
  },
  {
   "bugid": 1955890,
   "status": "RESOLVED",
   "component": "Firefox for Android:Settings",
   "summary": "[app icon picker] Add an icon selection fragment"
  },
  {
   "bugid": 1976776,
   "status": "RESOLVED",
   "component": "Firefox for Android:Settings",
   "summary": "[app icon picker] Add an app restart warning dialog"
  },
  {
   "bugid": 1977906,
   "status": "RESOLVED",
   "component": "Firefox for Android:Settings",
   "summary": "[app icon picker] Refactor/simplify the data layer"
  },
  {
   "bugid": 1890779,
   "status": "RESOLVED",
   "component": "Firefox for Android:Tabs",
   "summary": "[Tab Strip] New Tab button not opening new tab immediately on tab strip"
  },
  {
   "bugid": 1948761,
   "status": "RESOLVED",
   "component": "Firefox for Android:Toolbar",
   "summary": "[composable toolbar] Configure the QR scan button"
  },
  {
   "bugid": 1969335,
   "status": "RESOLVED",
   "component": "Firefox for Android:Toolbar",
   "summary": "[composable toolbar] build the QR button and connect to AppState"
  },
  {
   "bugid": 1970653,
   "status": "RESOLVED",
   "component": "Firefox for Android:Toolbar",
   "summary": "Use fake instead of mock for URL Render tests"
  },
  {
   "bugid": 1978398,
   "status": "RESOLVED",
   "component": "Firefox for Android:Toolbar",
   "summary": "[toolbar redesign] Show navbar with tabstrip"
  },
  {
   "bugid": 1978810,
   "status": "RESOLVED",
   "component": "Firefox for Android:Toolbar",
   "summary": "[Menu Redesign] Update the menu to incorporate the system navigation bar"
  },
  {
   "bugid": 1971478,
   "status": "RESOLVED",
   "component": "Firefox for Android:UI Tests",
   "summary": "Intermittent UI test failure - < BookmarksTest. createBookmarkFolderTest >"
  },
  {
   "bugid": 1977818,
   "status": "RESOLVED",
   "component": "Firefox for Android:UI Tests",
   "summary": "Intermittent UI test failure - < MainMenuTestCompose. verifyTheExtensionsdMenuListAfterRemovingAnExtensionTest >"
  },
  {
   "bugid": 1970225,
   "status": "RESOLVED",
   "component": "GeckoView:General",
   "summary": "[GeckoView] Multi - Get and Set Gecko Preferences"
  },
  {
   "bugid": 1963657,
   "status": "RESOLVED",
   "component": "Mozilla QA:Update Testing",
   "summary": "Wire Update Testing to update-verify"
  },
  {
   "bugid": 1927797,
   "status": "REOPENED",
   "component": "NSS:Libraries",
   "summary": "Certificate Compression for QUIC"
  },
  {
   "bugid": 1978533,
   "status": "RESOLVED",
   "component": "Remote Protocol:WebDriver BiDi",
   "summary": "locale override is not inheritted to newly created cross-origin iframes"
  },
  {
   "bugid": 1978795,
   "status": "RESOLVED",
   "component": "Toolkit:Crash Reporting",
   "summary": "Remove the step that installs lipo in the system-symbols-mac Docker image"
  },
  {
   "bugid": 1978424,
   "status": "RESOLVED",
   "component": "Toolkit:Gecko Trace",
   "summary": "Update opentelemetry-cpp to new version v1.22.0 from 2025-07-12 00:11:41"
  },
  {
   "bugid": 1978876,
   "status": "RESOLVED",
   "component": "Toolkit:Places",
   "summary": "Semantic history is wrongly limited to 600 entries"
  },
  {
   "bugid": 283779,
   "status": "ASSIGNED",
   "component": "Toolkit:Startup and Profile System",
   "summary": "Enhancement: Add a flag to provide an alternate 'Application Data' directory"
  },
  {
   "bugid": 1908535,
   "status": "RESOLVED",
   "component": "Toolkit:UI Widgets",
   "summary": "Remove the \"--input-space-block\" token"
  },
  {
   "bugid": 1971526,
   "status": "REOPENED",
   "component": "Toolkit:UI Widgets",
   "summary": "Add some reasonable toolbar separator styles to toolkit"
  },
  {
   "bugid": 1977865,
   "status": "RESOLVED",
   "component": "Toolkit:UI Widgets",
   "summary": "PanelList positioning should be relative to document.body when in content pages"
  },
  {
   "bugid": 1952788,
   "status": "RESOLVED",
   "component": "Web Compatibility:Site Reports",
   "summary": "m.youtube.com - Redirects to homepage when going back after accessing a video from search results"
  },
  {
   "bugid": 1978614,
   "status": "RESOLVED",
   "component": "WebExtensions:General",
   "summary": "Add support for a `has_previous_consent` flag in the manifest"
  },
  {
   "bugid": 1979063,
   "status": "RESOLVED",
   "component": "WebExtensions:General",
   "summary": "Work around intermitent failure caused by use of storage.local in test_ext_listener_proxies.html"
  },
  {
   "bugid": 1910669,
   "status": "RESOLVED",
   "component": "WebExtensions:Storage",
   "summary": "Implement StorageArea.getKeys() in extension storage API"
  }
 ],
 "fixed": 79,
 "total": 94,
 "restricted": 1
}